wagtailforums/models.py
wagtailforums/__init__.py
wagtailforums-0.1a3.dist-info/metadata.json
wagtailforums-0.1a3.dist-info/WHEEL
wagtailforums-0.1a3.dist-info/top_level.txt
wagtailforums-0.1a3.dist-info/METADATA
wagtailforums-0.1a3.dist-info/RECORD
wagtailforums-0.1a3.dist-info/DESCRIPTION.rst
