Metadata-Version: 2.0
Name: wagtailforums
Version: 0.1a3
Summary: A simple forum system for Wagtail CMS
Home-page: https://github.com/kaedroho/wagtailforums
Author: Karl Hobley
Author-email: karlhobley10@gmail.com
License: BSD
Platform: UNKNOWN
Classifier: Development Status :: 4 - Beta
Classifier: Environment :: Web Environment
Classifier: Intended Audience :: Developers
Classifier: License :: OSI Approved :: BSD License
Classifier: Operating System :: OS Independent
Classifier: Programming Language :: Python
Classifier: Programming Language :: Python :: 2
Classifier: Programming Language :: Python :: 2.6
Classifier: Programming Language :: Python :: 2.7
Classifier: Programming Language :: Python :: 3
Classifier: Programming Language :: Python :: 3.2
Classifier: Programming Language :: Python :: 3.3
Classifier: Programming Language :: Python :: 3.4
Classifier: Framework :: Django
Classifier: Topic :: Internet :: WWW/HTTP :: Site Management
Requires-Dist: Django (>=1.7,<1.8)
Requires-Dist: wagtail (>=1.0,<1.1)
